<?xml version="1.0" encoding="windows-1252" ?>
<!DOCTYPE ViewObject SYSTEM "jbo_03_01.dtd">
<!---->
<ViewObject
  xmlns="http://xmlns.oracle.com/bc4j"
  Name="BookingVmsDtls_RoVo"
  Version="11.1.1.66.73"
  InheritPersonalization="merge"
  BindingStyle="OracleName"
  CustomQuery="true"
  PageIterMode="Full"
  UseGlueCode="false">
  <DesignTime>
    <Attr Name="_isExpertMode" Value="true"/>
  </DesignTime>
  <Properties>
    <SchemaBasedProperties>
      <LABEL
        ResId="custom.lease.model.ROVO.BookingVmsDtls_RoVo_LABEL"/>
    </SchemaBasedProperties>
  </Properties>
  <SQLQuery>
    <![CDATA[SELECT 
    XXPL_SEARCH_BOOKING_V.BOOKING_HDR_ID BOOKING_HDR_ID, 
    XXPL_SEARCH_BOOKING_V.ORG_ID ORG_ID, 
    XXPL_SEARCH_BOOKING_V.FUNC_ID FUNC_ID, 
    XXPL_SEARCH_BOOKING_V.PROPERTY_ID PROPERTY_ID, 
    XXPL_SEARCH_BOOKING_V.BUILDING BUILDING, 
    XXPL_SEARCH_BOOKING_V.BOOKING_NUMBER BOOKING_NUMBER, 
    XXPL_SEARCH_BOOKING_V.BOOKING_DATE BOOKING_DATE, 
    XXPL_SEARCH_BOOKING_V.BOOKING_LEASE_START_DATE BOOKING_LEASE_START_DATE, 
    XXPL_SEARCH_BOOKING_V.BOOKING_LEASE_END_DATE BOOKING_LEASE_END_DATE, 
    XXPL_SEARCH_BOOKING_V.NO_OF_DAYS as CONTRACT_DAYS,
    XXPL_SEARCH_BOOKING_V.MS_HDR_ID MS_HDR_ID, 
    mh.MILESTONE_NAME,
    XXPL_SEARCH_BOOKING_V.PL_ID PL_ID, 
    ph.pl_name,
    XXPL_SEARCH_BOOKING_V.CURRENCY_CODE CURRENCY_CODE, 
    XXPL_SEARCH_BOOKING_V.STATUS STATUS, 
    XXPL_SEARCH_BOOKING_V.DESCRIPTION DESCRIPTION, 
    XXPL_SEARCH_BOOKING_V.ATTRIBUTE_CATEGORY ATTRIBUTE_CATEGORY, 
    XXPL_SEARCH_BOOKING_V.ATTRIBUTE1 ATTRIBUTE1, 
    XXPL_SEARCH_BOOKING_V.ATTRIBUTE2 ATTRIBUTE2, 
    XXPL_SEARCH_BOOKING_V.ATTRIBUTE3 ATTRIBUTE3, 
    XXPL_SEARCH_BOOKING_V.ATTRIBUTE4 ATTRIBUTE4, 
    XXPL_SEARCH_BOOKING_V.ATTRIBUTE5 ATTRIBUTE5, 
    XXPL_SEARCH_BOOKING_V.ATTRIBUTE6 ATTRIBUTE6, 
    XXPL_SEARCH_BOOKING_V.ATTRIBUTE7 ATTRIBUTE7, 
    XXPL_SEARCH_BOOKING_V.ATTRIBUTE8 ATTRIBUTE8, 
    XXPL_SEARCH_BOOKING_V.ATTRIBUTE9 ATTRIBUTE9, 
    XXPL_SEARCH_BOOKING_V.ATTRIBUTE10 ATTRIBUTE10, 
    XXPL_SEARCH_BOOKING_V.CREATED_BY CREATED_BY, 
    XXPL_SEARCH_BOOKING_V.CREATION_DATE CREATION_DATE, 
    XXPL_SEARCH_BOOKING_V.LAST_UPDATED_BY LAST_UPDATED_BY, 
    XXPL_SEARCH_BOOKING_V.LAST_UPDATE_DATE LAST_UPDATE_DATE, 
    XXPL_SEARCH_BOOKING_V.LAST_UPDATE_LOGIN LAST_UPDATE_LOGIN, 
    XXPL_SEARCH_BOOKING_V.UNIT_ID UNIT_ID, 
    XXPL_SEARCH_BOOKING_V.AREA_IN_SQFT AREA_IN_SQFT, 
    XXPL_SEARCH_BOOKING_V.BASE_PRICE BASE_PRICE, 
    XXPL_SEARCH_BOOKING_V.BOOKING_AMOUNT BOOKING_AMOUNT, 
    XXPL_SEARCH_BOOKING_V.DISCOUNT_TYPE DISCOUNT_TYPE, 
    XXPL_SEARCH_BOOKING_V.DISC_PCT DISC_PCT, 
    XXPL_SEARCH_BOOKING_V.DISC_AMOUNT DISC_AMOUNT, 
    XXPL_SEARCH_BOOKING_V.TAX_CODE TAX_CODE, 
    XXPL_SEARCH_BOOKING_V.TAX_RATE TAX_RATE, 
    XXPL_SEARCH_BOOKING_V.TAX_AMOUNT TAX_AMOUNT, 
    XXPL_SEARCH_BOOKING_V.TOTAL_AMOUNT TOTAL_AMOUNT, 
    XXPL_SEARCH_BOOKING_V.ORG_NAME ORG_NAME, 
    XXPL_SEARCH_BOOKING_V.PROPERTY_NUMBER PROPERTY_NUMBER, 
    XXPL_SEARCH_BOOKING_V.PROPERTY_NAME PROPERTY_NAME, 
    XXPL_SEARCH_BOOKING_V.BUILD_NAME BUILD_NAME, 
    XXPL_SEARCH_BOOKING_V.BUILD_NUMBER BUILD_NUMBER, 
    XXPL_SEARCH_BOOKING_V.UNIT_NAME UNIT_NAME, 
    XXPL_SEARCH_BOOKING_V.UNIT_NUMBER UNIT_NUMBER, 
    XXPL_SEARCH_BOOKING_V.CUSTOMER_NUMBER CUSTOMER_NUMBER, 
    XXPL_SEARCH_BOOKING_V.CUSTOMER_NAME CUSTOMER_NAME,
    bm.BOOKING_MS_DTL_ID,
    bm.SEQ_NUMBER, 
    bm.MILESTONE_TYPE, 
    bm.INSTALLMENT_TYPE, 
    bm.CARPARKING_ID, 
    bm.CHARGE_NAME, 
    bm.INSTALLMENT_PCT, 
    bm.BASEAMOUNT as MS_BASEAMOUNT, 
    bm.TAX_RATE as MS_TAX_RATE, 
    bm.TAX_CODE as MS_TAX_CODE, 
    bm.TAX_AMOUNT MS_TAX_AMOUNT, 
    bm.INSTALLMENT_AMOUNT, 
    bm.CHARGE_TYPE, 
    bm.PAYMENT_TERM, 
    bm.START_DATE, 
    bm.DUE_DATE, 
    bm.REMARKS
   
FROM 
    XXPL_SEARCH_BOOKING_V,xxpl_booking_milestones bm,xxpl_milestones_hdr mh,xxpl_pl_header ph
    where XXPL_SEARCH_BOOKING_V.BOOKING_HDR_ID=bm.BOOKING_HDR_ID
    and XXPL_SEARCH_BOOKING_V.MS_HDR_ID=mh.MS_HDR_ID
    and XXPL_SEARCH_BOOKING_V.PL_ID=ph.PL_ID
ORDER BY XXPL_SEARCH_BOOKING_V.BOOKING_HDR_ID,bm.MILESTONE_TYPE,bm.SEQ_NUMBER DESC]]>
  </SQLQuery>
  <ViewAttribute
    Name="BookingHdrId"
    IsUpdateable="false"
    IsPersistent="false"
    IsNotNull="true"
    PrecisionRule="true"
    Type="java.math.BigDecimal"
    ColumnType="BIGINT"
    AliasName="BOOKING_HDR_ID"
    Expression="BOOKING_HDR_ID"
    SQLType="NUMERIC">
    <DesignTime>
      <Attr Name="_DisplaySize" Value="39"/>
    </DesignTime>
  </ViewAttribute>
  <ViewAttribute
    Name="OrgId"
    IsUpdateable="false"
    IsPersistent="false"
    PrecisionRule="true"
    Type="java.math.BigDecimal"
    ColumnType="NUMBER"
    AliasName="ORG_ID"
    Expression="ORG_ID"
    SQLType="NUMERIC">
    <DesignTime>
      <Attr Name="_DisplaySize" Value="39"/>
    </DesignTime>
  </ViewAttribute>
  <ViewAttribute
    Name="FuncId"
    IsUpdateable="false"
    IsPersistent="false"
    PrecisionRule="true"
    Type="java.math.BigDecimal"
    ColumnType="NUMBER"
    AliasName="FUNC_ID"
    Expression="FUNC_ID"
    SQLType="NUMERIC">
    <DesignTime>
      <Attr Name="_DisplaySize" Value="39"/>
    </DesignTime>
  </ViewAttribute>
  <ViewAttribute
    Name="PropertyId"
    IsUpdateable="false"
    IsPersistent="false"
    IsNotNull="true"
    PrecisionRule="true"
    Type="java.math.BigDecimal"
    ColumnType="NUMBER"
    AliasName="PROPERTY_ID"
    Expression="PROPERTY_ID"
    SQLType="NUMERIC">
    <DesignTime>
      <Attr Name="_DisplaySize" Value="39"/>
    </DesignTime>
  </ViewAttribute>
  <ViewAttribute
    Name="Building"
    IsUpdateable="false"
    IsPersistent="false"
    IsNotNull="true"
    PrecisionRule="true"
    Type="java.math.BigDecimal"
    ColumnType="NUMBER"
    AliasName="BUILDING"
    Expression="BUILDING"
    SQLType="NUMERIC">
    <DesignTime>
      <Attr Name="_DisplaySize" Value="39"/>
    </DesignTime>
  </ViewAttribute>
  <ViewAttribute
    Name="BookingNumber"
    IsUpdateable="false"
    IsPersistent="false"
    PrecisionRule="true"
    Precision="60"
    Type="java.lang.String"
    ColumnType="VARCHAR2"
    AliasName="BOOKING_NUMBER"
    Expression="BOOKING_NUMBER"
    SQLType="VARCHAR">
    <DesignTime>
      <Attr Name="_DisplaySize" Value="60"/>
    </DesignTime>
  </ViewAttribute>
  <ViewAttribute
    Name="BookingDate"
    IsUpdateable="false"
    IsPersistent="false"
    PrecisionRule="true"
    Type="java.sql.Date"
    ColumnType="DATE"
    AliasName="BOOKING_DATE"
    Expression="BOOKING_DATE"
    SQLType="DATE">
    <DesignTime>
      <Attr Name="_DisplaySize" Value="7"/>
    </DesignTime>
  </ViewAttribute>
  <ViewAttribute
    Name="BookingLeaseStartDate"
    IsUpdateable="false"
    IsPersistent="false"
    PrecisionRule="true"
    Type="java.sql.Date"
    ColumnType="DATE"
    AliasName="BOOKING_LEASE_START_DATE"
    Expression="BOOKING_LEASE_START_DATE"
    SQLType="DATE">
    <DesignTime>
      <Attr Name="_DisplaySize" Value="7"/>
    </DesignTime>
  </ViewAttribute>
  <ViewAttribute
    Name="BookingLeaseEndDate"
    IsUpdateable="false"
    IsPersistent="false"
    PrecisionRule="true"
    Type="java.sql.Date"
    ColumnType="DATE"
    AliasName="BOOKING_LEASE_END_DATE"
    Expression="BOOKING_LEASE_END_DATE"
    SQLType="DATE">
    <DesignTime>
      <Attr Name="_DisplaySize" Value="7"/>
    </DesignTime>
  </ViewAttribute>
  <ViewAttribute
    Name="ContractDays"
    IsUpdateable="false"
    IsPersistent="false"
    PrecisionRule="true"
    Type="java.math.BigDecimal"
    ColumnType="NUMBER"
    AliasName="CONTRACT_DAYS"
    Expression="CONTRACT_DAYS"
    SQLType="NUMERIC">
    <DesignTime>
      <Attr Name="_DisplaySize" Value="39"/>
    </DesignTime>
  </ViewAttribute>
  <ViewAttribute
    Name="MsHdrId"
    IsUpdateable="false"
    IsPersistent="false"
    PrecisionRule="true"
    Type="java.math.BigDecimal"
    ColumnType="NUMBER"
    AliasName="MS_HDR_ID"
    Expression="MS_HDR_ID"
    SQLType="NUMERIC">
    <DesignTime>
      <Attr Name="_DisplaySize" Value="39"/>
    </DesignTime>
  </ViewAttribute>
  <ViewAttribute
    Name="MilestoneName"
    IsUpdateable="false"
    IsPersistent="false"
    IsNotNull="true"
    PrecisionRule="true"
    Precision="240"
    Type="java.lang.String"
    ColumnType="VARCHAR2"
    AliasName="MILESTONE_NAME"
    Expression="MILESTONE_NAME"
    SQLType="VARCHAR">
    <DesignTime>
      <Attr Name="_DisplaySize" Value="240"/>
    </DesignTime>
  </ViewAttribute>
  <ViewAttribute
    Name="PlId"
    IsUpdateable="false"
    IsPersistent="false"
    PrecisionRule="true"
    Type="java.math.BigDecimal"
    ColumnType="NUMBER"
    AliasName="PL_ID"
    Expression="PL_ID"
    SQLType="NUMERIC">
    <DesignTime>
      <Attr Name="_DisplaySize" Value="39"/>
    </DesignTime>
  </ViewAttribute>
  <ViewAttribute
    Name="PlName"
    IsUpdateable="false"
    IsPersistent="false"
    IsNotNull="true"
    PrecisionRule="true"
    Precision="60"
    Type="java.lang.String"
    ColumnType="VARCHAR2"
    AliasName="PL_NAME"
    Expression="PL_NAME"
    SQLType="VARCHAR">
    <DesignTime>
      <Attr Name="_DisplaySize" Value="60"/>
    </DesignTime>
  </ViewAttribute>
  <ViewAttribute
    Name="CurrencyCode"
    IsUpdateable="false"
    IsPersistent="false"
    PrecisionRule="true"
    Precision="3"
    Type="java.lang.String"
    ColumnType="VARCHAR2"
    AliasName="CURRENCY_CODE"
    Expression="CURRENCY_CODE"
    SQLType="VARCHAR">
    <DesignTime>
      <Attr Name="_DisplaySize" Value="3"/>
    </DesignTime>
  </ViewAttribute>
  <ViewAttribute
    Name="Status"
    IsUpdateable="false"
    IsPersistent="false"
    PrecisionRule="true"
    Precision="60"
    Type="java.lang.String"
    ColumnType="VARCHAR2"
    AliasName="STATUS"
    Expression="STATUS"
    SQLType="VARCHAR">
    <DesignTime>
      <Attr Name="_DisplaySize" Value="60"/>
    </DesignTime>
  </ViewAttribute>
  <ViewAttribute
    Name="Description"
    IsUpdateable="false"
    IsPersistent="false"
    PrecisionRule="true"
    Precision="240"
    Type="java.lang.String"
    ColumnType="VARCHAR2"
    AliasName="DESCRIPTION"
    Expression="DESCRIPTION"
    SQLType="VARCHAR">
    <DesignTime>
      <Attr Name="_DisplaySize" Value="240"/>
    </DesignTime>
  </ViewAttribute>
  <ViewAttribute
    Name="AttributeCategory"
    IsUpdateable="false"
    IsPersistent="false"
    PrecisionRule="true"
    Precision="240"
    Type="java.lang.String"
    ColumnType="VARCHAR2"
    AliasName="ATTRIBUTE_CATEGORY"
    Expression="ATTRIBUTE_CATEGORY"
    SQLType="VARCHAR">
    <DesignTime>
      <Attr Name="_DisplaySize" Value="240"/>
    </DesignTime>
  </ViewAttribute>
  <ViewAttribute
    Name="Attribute1"
    IsUpdateable="false"
    IsPersistent="false"
    PrecisionRule="true"
    Precision="240"
    Type="java.lang.String"
    ColumnType="VARCHAR2"
    AliasName="ATTRIBUTE1"
    Expression="ATTRIBUTE1"
    SQLType="VARCHAR">
    <DesignTime>
      <Attr Name="_DisplaySize" Value="240"/>
    </DesignTime>
  </ViewAttribute>
  <ViewAttribute
    Name="Attribute2"
    IsUpdateable="false"
    IsPersistent="false"
    PrecisionRule="true"
    Precision="240"
    Type="java.lang.String"
    ColumnType="VARCHAR2"
    AliasName="ATTRIBUTE2"
    Expression="ATTRIBUTE2"
    SQLType="VARCHAR">
    <DesignTime>
      <Attr Name="_DisplaySize" Value="240"/>
    </DesignTime>
  </ViewAttribute>
  <ViewAttribute
    Name="Attribute3"
    IsUpdateable="false"
    IsPersistent="false"
    PrecisionRule="true"
    Precision="240"
    Type="java.lang.String"
    ColumnType="VARCHAR2"
    AliasName="ATTRIBUTE3"
    Expression="ATTRIBUTE3"
    SQLType="VARCHAR">
    <DesignTime>
      <Attr Name="_DisplaySize" Value="240"/>
    </DesignTime>
  </ViewAttribute>
  <ViewAttribute
    Name="Attribute4"
    IsUpdateable="false"
    IsPersistent="false"
    PrecisionRule="true"
    Precision="240"
    Type="java.lang.String"
    ColumnType="VARCHAR2"
    AliasName="ATTRIBUTE4"
    Expression="ATTRIBUTE4"
    SQLType="VARCHAR">
    <DesignTime>
      <Attr Name="_DisplaySize" Value="240"/>
    </DesignTime>
  </ViewAttribute>
  <ViewAttribute
    Name="Attribute5"
    IsUpdateable="false"
    IsPersistent="false"
    PrecisionRule="true"
    Precision="240"
    Type="java.lang.String"
    ColumnType="VARCHAR2"
    AliasName="ATTRIBUTE5"
    Expression="ATTRIBUTE5"
    SQLType="VARCHAR">
    <DesignTime>
      <Attr Name="_DisplaySize" Value="240"/>
    </DesignTime>
  </ViewAttribute>
  <ViewAttribute
    Name="Attribute6"
    IsUpdateable="false"
    IsPersistent="false"
    PrecisionRule="true"
    Precision="240"
    Type="java.lang.String"
    ColumnType="VARCHAR2"
    AliasName="ATTRIBUTE6"
    Expression="ATTRIBUTE6"
    SQLType="VARCHAR">
    <DesignTime>
      <Attr Name="_DisplaySize" Value="240"/>
    </DesignTime>
  </ViewAttribute>
  <ViewAttribute
    Name="Attribute7"
    IsUpdateable="false"
    IsPersistent="false"
    PrecisionRule="true"
    Precision="240"
    Type="java.lang.String"
    ColumnType="VARCHAR2"
    AliasName="ATTRIBUTE7"
    Expression="ATTRIBUTE7"
    SQLType="VARCHAR">
    <DesignTime>
      <Attr Name="_DisplaySize" Value="240"/>
    </DesignTime>
  </ViewAttribute>
  <ViewAttribute
    Name="Attribute8"
    IsUpdateable="false"
    IsPersistent="false"
    PrecisionRule="true"
    Precision="240"
    Type="java.lang.String"
    ColumnType="VARCHAR2"
    AliasName="ATTRIBUTE8"
    Expression="ATTRIBUTE8"
    SQLType="VARCHAR">
    <DesignTime>
      <Attr Name="_DisplaySize" Value="240"/>
    </DesignTime>
  </ViewAttribute>
  <ViewAttribute
    Name="Attribute9"
    IsUpdateable="false"
    IsPersistent="false"
    PrecisionRule="true"
    Precision="240"
    Type="java.lang.String"
    ColumnType="VARCHAR2"
    AliasName="ATTRIBUTE9"
    Expression="ATTRIBUTE9"
    SQLType="VARCHAR">
    <DesignTime>
      <Attr Name="_DisplaySize" Value="240"/>
    </DesignTime>
  </ViewAttribute>
  <ViewAttribute
    Name="Attribute10"
    IsUpdateable="false"
    IsPersistent="false"
    PrecisionRule="true"
    Precision="240"
    Type="java.lang.String"
    ColumnType="VARCHAR2"
    AliasName="ATTRIBUTE10"
    Expression="ATTRIBUTE10"
    SQLType="VARCHAR">
    <DesignTime>
      <Attr Name="_DisplaySize" Value="240"/>
    </DesignTime>
  </ViewAttribute>
  <ViewAttribute
    Name="CreatedBy"
    IsUpdateable="false"
    IsPersistent="false"
    IsNotNull="true"
    PrecisionRule="true"
    Precision="60"
    Type="java.lang.String"
    ColumnType="VARCHAR2"
    AliasName="CREATED_BY"
    Expression="CREATED_BY"
    SQLType="VARCHAR">
    <DesignTime>
      <Attr Name="_DisplaySize" Value="60"/>
    </DesignTime>
  </ViewAttribute>
  <ViewAttribute
    Name="CreationDate"
    IsUpdateable="false"
    IsPersistent="false"
    IsNotNull="true"
    PrecisionRule="true"
    Type="java.sql.Timestamp"
    ColumnType="TIMESTAMP"
    AliasName="CREATION_DATE"
    Expression="CREATION_DATE"
    SQLType="TIMESTAMP">
    <DesignTime>
      <Attr Name="_DisplaySize" Value="11"/>
    </DesignTime>
  </ViewAttribute>
  <ViewAttribute
    Name="LastUpdatedBy"
    IsUpdateable="false"
    IsPersistent="false"
    IsNotNull="true"
    PrecisionRule="true"
    Precision="60"
    Type="java.lang.String"
    ColumnType="VARCHAR2"
    AliasName="LAST_UPDATED_BY"
    Expression="LAST_UPDATED_BY"
    SQLType="VARCHAR">
    <DesignTime>
      <Attr Name="_DisplaySize" Value="60"/>
    </DesignTime>
  </ViewAttribute>
  <ViewAttribute
    Name="LastUpdateDate"
    IsUpdateable="false"
    IsPersistent="false"
    IsNotNull="true"
    PrecisionRule="true"
    Type="java.sql.Timestamp"
    ColumnType="TIMESTAMP"
    AliasName="LAST_UPDATE_DATE"
    Expression="LAST_UPDATE_DATE"
    SQLType="TIMESTAMP">
    <DesignTime>
      <Attr Name="_DisplaySize" Value="11"/>
    </DesignTime>
  </ViewAttribute>
  <ViewAttribute
    Name="LastUpdateLogin"
    IsUpdateable="false"
    IsPersistent="false"
    IsNotNull="true"
    PrecisionRule="true"
    Precision="150"
    Type="java.lang.String"
    ColumnType="VARCHAR2"
    AliasName="LAST_UPDATE_LOGIN"
    Expression="LAST_UPDATE_LOGIN"
    SQLType="VARCHAR">
    <DesignTime>
      <Attr Name="_DisplaySize" Value="150"/>
    </DesignTime>
  </ViewAttribute>
  <ViewAttribute
    Name="UnitId"
    IsUpdateable="false"
    IsPersistent="false"
    IsNotNull="true"
    PrecisionRule="true"
    Type="java.math.BigDecimal"
    ColumnType="NUMBER"
    AliasName="UNIT_ID"
    Expression="UNIT_ID"
    SQLType="NUMERIC">
    <DesignTime>
      <Attr Name="_DisplaySize" Value="39"/>
    </DesignTime>
  </ViewAttribute>
  <ViewAttribute
    Name="AreaInSqft"
    IsUpdateable="false"
    IsPersistent="false"
    PrecisionRule="true"
    Type="java.math.BigDecimal"
    ColumnType="NUMBER"
    AliasName="AREA_IN_SQFT"
    Expression="AREA_IN_SQFT"
    SQLType="NUMERIC">
    <DesignTime>
      <Attr Name="_DisplaySize" Value="39"/>
    </DesignTime>
  </ViewAttribute>
  <ViewAttribute
    Name="BasePrice"
    IsUpdateable="false"
    IsPersistent="false"
    PrecisionRule="true"
    Type="java.math.BigDecimal"
    ColumnType="NUMBER"
    AliasName="BASE_PRICE"
    Expression="BASE_PRICE"
    SQLType="NUMERIC">
    <DesignTime>
      <Attr Name="_DisplaySize" Value="39"/>
    </DesignTime>
  </ViewAttribute>
  <ViewAttribute
    Name="BookingAmount"
    IsUpdateable="false"
    IsPersistent="false"
    PrecisionRule="true"
    Type="java.math.BigDecimal"
    ColumnType="NUMBER"
    AliasName="BOOKING_AMOUNT"
    Expression="BOOKING_AMOUNT"
    SQLType="NUMERIC">
    <DesignTime>
      <Attr Name="_DisplaySize" Value="39"/>
    </DesignTime>
  </ViewAttribute>
  <ViewAttribute
    Name="DiscountType"
    IsUpdateable="false"
    IsPersistent="false"
    PrecisionRule="true"
    Precision="60"
    Type="java.lang.String"
    ColumnType="VARCHAR2"
    AliasName="DISCOUNT_TYPE"
    Expression="DISCOUNT_TYPE"
    SQLType="VARCHAR">
    <DesignTime>
      <Attr Name="_DisplaySize" Value="60"/>
    </DesignTime>
  </ViewAttribute>
  <ViewAttribute
    Name="DiscPct"
    IsUpdateable="false"
    IsPersistent="false"
    PrecisionRule="true"
    Type="java.math.BigDecimal"
    ColumnType="NUMBER"
    AliasName="DISC_PCT"
    Expression="DISC_PCT"
    SQLType="NUMERIC">
    <DesignTime>
      <Attr Name="_DisplaySize" Value="39"/>
    </DesignTime>
  </ViewAttribute>
  <ViewAttribute
    Name="DiscAmount"
    IsUpdateable="false"
    IsPersistent="false"
    PrecisionRule="true"
    Type="java.math.BigDecimal"
    ColumnType="NUMBER"
    AliasName="DISC_AMOUNT"
    Expression="DISC_AMOUNT"
    SQLType="NUMERIC">
    <DesignTime>
      <Attr Name="_DisplaySize" Value="39"/>
    </DesignTime>
  </ViewAttribute>
  <ViewAttribute
    Name="TaxCode"
    IsUpdateable="false"
    IsPersistent="false"
    PrecisionRule="true"
    Precision="60"
    Type="java.lang.String"
    ColumnType="VARCHAR2"
    AliasName="TAX_CODE"
    Expression="TAX_CODE"
    SQLType="VARCHAR">
    <DesignTime>
      <Attr Name="_DisplaySize" Value="60"/>
    </DesignTime>
  </ViewAttribute>
  <ViewAttribute
    Name="TaxRate"
    IsUpdateable="false"
    IsPersistent="false"
    PrecisionRule="true"
    Type="java.math.BigDecimal"
    ColumnType="NUMBER"
    AliasName="TAX_RATE"
    Expression="TAX_RATE"
    SQLType="NUMERIC">
    <DesignTime>
      <Attr Name="_DisplaySize" Value="39"/>
    </DesignTime>
  </ViewAttribute>
  <ViewAttribute
    Name="TaxAmount"
    IsUpdateable="false"
    IsPersistent="false"
    PrecisionRule="true"
    Type="java.math.BigDecimal"
    ColumnType="NUMBER"
    AliasName="TAX_AMOUNT"
    Expression="TAX_AMOUNT"
    SQLType="NUMERIC">
    <DesignTime>
      <Attr Name="_DisplaySize" Value="39"/>
    </DesignTime>
  </ViewAttribute>
  <ViewAttribute
    Name="TotalAmount"
    IsUpdateable="false"
    IsPersistent="false"
    PrecisionRule="true"
    Type="java.math.BigDecimal"
    ColumnType="NUMBER"
    AliasName="TOTAL_AMOUNT"
    Expression="TOTAL_AMOUNT"
    SQLType="NUMERIC">
    <DesignTime>
      <Attr Name="_DisplaySize" Value="39"/>
    </DesignTime>
  </ViewAttribute>
  <ViewAttribute
    Name="OrgName"
    IsUpdateable="false"
    IsPersistent="false"
    PrecisionRule="true"
    Precision="240"
    Type="java.lang.String"
    ColumnType="VARCHAR2"
    AliasName="ORG_NAME"
    Expression="ORG_NAME"
    SQLType="VARCHAR">
    <DesignTime>
      <Attr Name="_DisplaySize" Value="240"/>
    </DesignTime>
  </ViewAttribute>
  <ViewAttribute
    Name="PropertyNumber"
    IsUpdateable="false"
    IsPersistent="false"
    IsNotNull="true"
    PrecisionRule="true"
    Precision="60"
    Type="java.lang.String"
    ColumnType="VARCHAR2"
    AliasName="PROPERTY_NUMBER"
    Expression="PROPERTY_NUMBER"
    SQLType="VARCHAR">
    <DesignTime>
      <Attr Name="_DisplaySize" Value="60"/>
    </DesignTime>
  </ViewAttribute>
  <ViewAttribute
    Name="PropertyName"
    IsUpdateable="false"
    IsPersistent="false"
    IsNotNull="true"
    PrecisionRule="true"
    Precision="240"
    Type="java.lang.String"
    ColumnType="VARCHAR2"
    AliasName="PROPERTY_NAME"
    Expression="PROPERTY_NAME"
    SQLType="VARCHAR">
    <DesignTime>
      <Attr Name="_DisplaySize" Value="240"/>
    </DesignTime>
  </ViewAttribute>
  <ViewAttribute
    Name="BuildName"
    IsUpdateable="false"
    IsPersistent="false"
    IsNotNull="true"
    PrecisionRule="true"
    Precision="240"
    Type="java.lang.String"
    ColumnType="VARCHAR2"
    AliasName="BUILD_NAME"
    Expression="BUILD_NAME"
    SQLType="VARCHAR">
    <DesignTime>
      <Attr Name="_DisplaySize" Value="240"/>
    </DesignTime>
  </ViewAttribute>
  <ViewAttribute
    Name="BuildNumber"
    IsUpdateable="false"
    IsPersistent="false"
    IsNotNull="true"
    PrecisionRule="true"
    Precision="60"
    Type="java.lang.String"
    ColumnType="VARCHAR2"
    AliasName="BUILD_NUMBER"
    Expression="BUILD_NUMBER"
    SQLType="VARCHAR">
    <DesignTime>
      <Attr Name="_DisplaySize" Value="60"/>
    </DesignTime>
  </ViewAttribute>
  <ViewAttribute
    Name="UnitName"
    IsUpdateable="false"
    IsPersistent="false"
    IsNotNull="true"
    PrecisionRule="true"
    Precision="240"
    Type="java.lang.String"
    ColumnType="VARCHAR2"
    AliasName="UNIT_NAME"
    Expression="UNIT_NAME"
    SQLType="VARCHAR">
    <DesignTime>
      <Attr Name="_DisplaySize" Value="240"/>
    </DesignTime>
  </ViewAttribute>
  <ViewAttribute
    Name="UnitNumber"
    IsUpdateable="false"
    IsPersistent="false"
    IsNotNull="true"
    PrecisionRule="true"
    Precision="60"
    Type="java.lang.String"
    ColumnType="VARCHAR2"
    AliasName="UNIT_NUMBER"
    Expression="UNIT_NUMBER"
    SQLType="VARCHAR">
    <DesignTime>
      <Attr Name="_DisplaySize" Value="60"/>
    </DesignTime>
  </ViewAttribute>
  <ViewAttribute
    Name="CustomerNumber"
    IsUpdateable="false"
    IsPersistent="false"
    PrecisionRule="true"
    Precision="30"
    Type="java.lang.String"
    ColumnType="VARCHAR2"
    AliasName="CUSTOMER_NUMBER"
    Expression="CUSTOMER_NUMBER"
    SQLType="VARCHAR">
    <DesignTime>
      <Attr Name="_DisplaySize" Value="30"/>
    </DesignTime>
  </ViewAttribute>
  <ViewAttribute
    Name="CustomerName"
    IsUpdateable="false"
    IsPersistent="false"
    PrecisionRule="true"
    Precision="240"
    Type="java.lang.String"
    ColumnType="VARCHAR2"
    AliasName="CUSTOMER_NAME"
    Expression="CUSTOMER_NAME"
    SQLType="VARCHAR">
    <DesignTime>
      <Attr Name="_DisplaySize" Value="240"/>
    </DesignTime>
  </ViewAttribute>
  <ViewAttribute
    Name="BookingMsDtlId"
    IsUpdateable="false"
    IsPersistent="false"
    IsNotNull="true"
    PrecisionRule="true"
    Type="java.math.BigDecimal"
    ColumnType="NUMBER"
    AliasName="BOOKING_MS_DTL_ID"
    Expression="BOOKING_MS_DTL_ID"
    SQLType="NUMERIC">
    <DesignTime>
      <Attr Name="_DisplaySize" Value="39"/>
    </DesignTime>
  </ViewAttribute>
  <ViewAttribute
    Name="SeqNumber"
    IsUpdateable="false"
    IsPersistent="false"
    PrecisionRule="true"
    Type="java.math.BigDecimal"
    ColumnType="NUMBER"
    AliasName="SEQ_NUMBER"
    Expression="SEQ_NUMBER"
    SQLType="NUMERIC">
    <DesignTime>
      <Attr Name="_DisplaySize" Value="39"/>
    </DesignTime>
  </ViewAttribute>
  <ViewAttribute
    Name="MilestoneType"
    IsUpdateable="false"
    IsPersistent="false"
    PrecisionRule="true"
    Precision="60"
    Type="java.lang.String"
    ColumnType="VARCHAR2"
    AliasName="MILESTONE_TYPE"
    Expression="MILESTONE_TYPE"
    SQLType="VARCHAR">
    <DesignTime>
      <Attr Name="_DisplaySize" Value="60"/>
    </DesignTime>
  </ViewAttribute>
  <ViewAttribute
    Name="InstallmentType"
    IsUpdateable="false"
    IsPersistent="false"
    PrecisionRule="true"
    Precision="60"
    Type="java.lang.String"
    ColumnType="VARCHAR2"
    AliasName="INSTALLMENT_TYPE"
    Expression="INSTALLMENT_TYPE"
    SQLType="VARCHAR">
    <DesignTime>
      <Attr Name="_DisplaySize" Value="60"/>
    </DesignTime>
  </ViewAttribute>
  <ViewAttribute
    Name="CarparkingId"
    IsUpdateable="false"
    IsPersistent="false"
    PrecisionRule="true"
    Precision="200"
    Type="java.lang.String"
    ColumnType="VARCHAR2"
    AliasName="CARPARKING_ID"
    Expression="CARPARKING_ID"
    SQLType="VARCHAR">
    <DesignTime>
      <Attr Name="_DisplaySize" Value="200"/>
    </DesignTime>
  </ViewAttribute>
  <ViewAttribute
    Name="ChargeName"
    IsUpdateable="false"
    IsPersistent="false"
    PrecisionRule="true"
    Precision="60"
    Type="java.lang.String"
    ColumnType="VARCHAR2"
    AliasName="CHARGE_NAME"
    Expression="CHARGE_NAME"
    SQLType="VARCHAR">
    <DesignTime>
      <Attr Name="_DisplaySize" Value="60"/>
    </DesignTime>
  </ViewAttribute>
  <ViewAttribute
    Name="InstallmentPct"
    IsUpdateable="false"
    IsPersistent="false"
    PrecisionRule="true"
    Type="java.math.BigDecimal"
    ColumnType="NUMBER"
    AliasName="INSTALLMENT_PCT"
    Expression="INSTALLMENT_PCT"
    SQLType="NUMERIC">
    <DesignTime>
      <Attr Name="_DisplaySize" Value="39"/>
    </DesignTime>
  </ViewAttribute>
  <ViewAttribute
    Name="MsBaseamount"
    IsUpdateable="false"
    IsPersistent="false"
    PrecisionRule="true"
    Type="java.math.BigDecimal"
    ColumnType="NUMBER"
    AliasName="MS_BASEAMOUNT"
    Expression="MS_BASEAMOUNT"
    SQLType="NUMERIC">
    <DesignTime>
      <Attr Name="_DisplaySize" Value="39"/>
    </DesignTime>
  </ViewAttribute>
  <ViewAttribute
    Name="MsTaxRate"
    IsUpdateable="false"
    IsPersistent="false"
    PrecisionRule="true"
    Type="java.math.BigDecimal"
    ColumnType="NUMBER"
    AliasName="MS_TAX_RATE"
    Expression="MS_TAX_RATE"
    SQLType="NUMERIC">
    <DesignTime>
      <Attr Name="_DisplaySize" Value="39"/>
    </DesignTime>
  </ViewAttribute>
  <ViewAttribute
    Name="MsTaxCode"
    IsUpdateable="false"
    IsPersistent="false"
    PrecisionRule="true"
    Precision="60"
    Type="java.lang.String"
    ColumnType="VARCHAR2"
    AliasName="MS_TAX_CODE"
    Expression="MS_TAX_CODE"
    SQLType="VARCHAR">
    <DesignTime>
      <Attr Name="_DisplaySize" Value="60"/>
    </DesignTime>
  </ViewAttribute>
  <ViewAttribute
    Name="MsTaxAmount"
    IsUpdateable="false"
    IsPersistent="false"
    PrecisionRule="true"
    Type="java.math.BigDecimal"
    ColumnType="NUMBER"
    AliasName="MS_TAX_AMOUNT"
    Expression="MS_TAX_AMOUNT"
    SQLType="NUMERIC">
    <DesignTime>
      <Attr Name="_DisplaySize" Value="39"/>
    </DesignTime>
  </ViewAttribute>
  <ViewAttribute
    Name="InstallmentAmount"
    IsUpdateable="false"
    IsPersistent="false"
    PrecisionRule="true"
    Type="java.math.BigDecimal"
    ColumnType="NUMBER"
    AliasName="INSTALLMENT_AMOUNT"
    Expression="INSTALLMENT_AMOUNT"
    SQLType="NUMERIC">
    <DesignTime>
      <Attr Name="_DisplaySize" Value="39"/>
    </DesignTime>
  </ViewAttribute>
  <ViewAttribute
    Name="ChargeType"
    IsUpdateable="false"
    IsPersistent="false"
    PrecisionRule="true"
    Precision="60"
    Type="java.lang.String"
    ColumnType="VARCHAR2"
    AliasName="CHARGE_TYPE"
    Expression="CHARGE_TYPE"
    SQLType="VARCHAR">
    <DesignTime>
      <Attr Name="_DisplaySize" Value="60"/>
    </DesignTime>
  </ViewAttribute>
  <ViewAttribute
    Name="PaymentTerm"
    IsUpdateable="false"
    IsPersistent="false"
    PrecisionRule="true"
    Precision="60"
    Type="java.lang.String"
    ColumnType="VARCHAR2"
    AliasName="PAYMENT_TERM"
    Expression="PAYMENT_TERM"
    SQLType="VARCHAR">
    <DesignTime>
      <Attr Name="_DisplaySize" Value="60"/>
    </DesignTime>
  </ViewAttribute>
  <ViewAttribute
    Name="StartDate"
    IsUpdateable="false"
    IsPersistent="false"
    PrecisionRule="true"
    Type="java.sql.Date"
    ColumnType="DATE"
    AliasName="START_DATE"
    Expression="START_DATE"
    SQLType="DATE">
    <DesignTime>
      <Attr Name="_DisplaySize" Value="7"/>
    </DesignTime>
  </ViewAttribute>
  <ViewAttribute
    Name="DueDate"
    IsUpdateable="false"
    IsPersistent="false"
    PrecisionRule="true"
    Type="java.sql.Date"
    ColumnType="DATE"
    AliasName="DUE_DATE"
    Expression="DUE_DATE"
    SQLType="DATE">
    <DesignTime>
      <Attr Name="_DisplaySize" Value="7"/>
    </DesignTime>
  </ViewAttribute>
  <ViewAttribute
    Name="Remarks"
    IsUpdateable="false"
    IsPersistent="false"
    PrecisionRule="true"
    Precision="4000"
    Type="java.lang.String"
    ColumnType="VARCHAR2"
    AliasName="REMARKS"
    Expression="REMARKS"
    SQLType="VARCHAR">
    <DesignTime>
      <Attr Name="_DisplaySize" Value="4000"/>
    </DesignTime>
  </ViewAttribute>
  <AttrArray Name="KeyAttributes">
    <Item Value="BookingHdrId"/>
    <Item Value="BookingMsDtlId"/>
  </AttrArray>
  <ResourceBundle>
    <PropertiesBundle
      PropertiesFile="custom.lease.model.CustomLeaseModelBundle"/>
  </ResourceBundle>
</ViewObject>
